sqlmodel_repo/__init__.py
sqlmodel_repo/async_repo.py
sqlmodel_repo/sqlmodel_repo.py
sqlmodel_repo-0.0.4.dist-info/LICENSE
sqlmodel_repo-0.0.4.dist-info/METADATA
sqlmodel_repo-0.0.4.dist-info/WHEEL
sqlmodel_repo-0.0.4.dist-info/top_level.txt
sqlmodel_repo-0.0.4.dist-info/RECORD
