Metadata-Version: 2.1
Name: sqlmodel_repo
Version: 0.0.4
Summary: Active record mixin for SQLModel
Keywords: sqlmodel,sqlalchemy,orm,active record
Requires-Python: >3.11.0
License-File: LICENSE
Requires-Dist: sqlmodel
Provides-Extra: async
Requires-Dist: sqlalchemy[asyncio]; extra == "async"
